scoords/__init__.py
scoords/_version.py
scoords/attitude.py
scoords/spacecraft_frame.py
scoords-0.0.2.dist-info/METADATA
scoords-0.0.2.dist-info/WHEEL
scoords-0.0.2.dist-info/top_level.txt
scoords-0.0.2.dist-info/RECORD
