Metadata-Version: 2.1
Name: scoords
Version: 0.0.2
Summary: Spacecraft coordinates.
Home-page: https://github.com/cositools/scoords
Author: COSI Team
Author-email: imc@umd.edu
Requires-Dist: numpy
Requires-Dist: scipy
Requires-Dist: astropy
